mcp_diagrams/__init__.py
mcp_diagrams/__main__.py
mcp_diagrams/architecture_validator.py
mcp_diagrams/custom_nodes.py
mcp_diagrams/diagram_builder.py
mcp_diagrams/diagram_validator.py
mcp_diagrams/icon_validator.py
mcp_diagrams/metrics.py
mcp_diagrams/models.py
mcp_diagrams/provider_registry.py
mcp_diagrams/server.py
mcp_diagrams/service_aliases.json
mcp_diagrams/session_manager.py
mcp_diagrams/utils.py
mcp_diagrams-1.5.1.dist-info/licenses/LICENSE
mcp_diagrams-1.5.1.dist-info/METADATA
mcp_diagrams-1.5.1.dist-info/WHEEL
mcp_diagrams-1.5.1.dist-info/entry_points.txt
mcp_diagrams-1.5.1.dist-info/top_level.txt
mcp_diagrams-1.5.1.dist-info/RECORD
