Metadata-Version: 2.4
Name: mcp-diagrams
Version: 1.5.1
Summary: Create infrastructure and architecture diagrams via MCP
Author-email: Ravi Kiran <vrknetha@gmail.com>
License: MIT License
Project-URL: Homepage, https://github.com/vrknetha/mcp-diagrams
Project-URL: Documentation, https://github.com/vrknetha/mcp-diagrams#readme
Project-URL: Repository, https://github.com/vrknetha/mcp-diagrams.git
Project-URL: Bug Tracker, https://github.com/vrknetha/mcp-diagrams/issues
Keywords: mcp,diagrams,architecture,infrastructure,cloud,aws,azure,gcp,kubernetes
Classifier: Development Status :: 4 - Beta
Classifier: Intended Audience :: Developers
Classifier: License :: OSI Approved :: MIT License
Classifier: Programming Language :: Python :: 3
Classifier: Programming Language :: Python :: 3.10
Classifier: Programming Language :: Python :: 3.11
Classifier: Programming Language :: Python :: 3.12
Classifier: Topic :: Software Development :: Libraries
Classifier: Topic :: System :: Systems Administration
Requires-Python: >=3.10
License-File: LICENSE
Requires-Dist: fastmcp>=0.1.0
Requires-Dist: diagrams>=0.23.0
Requires-Dist: python-dotenv>=1.0.0
Requires-Dist: pydantic>=2.0.0
Provides-Extra: dev
Requires-Dist: pytest>=7.4.0; extra == "dev"
Requires-Dist: pytest-cov>=4.0.0; extra == "dev"
Requires-Dist: pytest-asyncio>=0.21.0; extra == "dev"
Requires-Dist: black>=23.0.0; extra == "dev"
Requires-Dist: ruff>=0.1.0; extra == "dev"
Requires-Dist: mypy>=1.5.0; extra == "dev"
Provides-Extra: test
Requires-Dist: pytest>=7.4.0; extra == "test"
Requires-Dist: pytest-cov>=4.0.0; extra == "test"
Requires-Dist: pytest-asyncio>=0.21.0; extra == "test"
Dynamic: license-file
